{
  "generatedAt": "2026-06-12T05:13:58.553Z",
  "sources": [
    "Stooq",
    "CoinGecko"
  ],
  "quotes": {
    "BTC": {
      "name": "BTC",
      "price": 63394,
      "prevClose": 62542.45612089954,
      "change": 851.5438791004635,
      "pct": 1.361545311642973
    }
  },
  "futures": {
    "BTC": {
      "name": "BTC",
      "price": 63394,
      "prevClose": 62542.45612089954,
      "change": 851.5438791004635,
      "pct": 1.361545311642973
    }
  },
  "errors": [
    "Error: 404 Not Found for https://stooq.com/q/l/?s=%5Espx&f=sd2t2ohlcvp&h&e=csv",
    "Error: 404 Not Found for https://stooq.com/q/l/?s=%5Endq&f=sd2t2ohlcvp&h&e=csv",
    "Error: 404 Not Found for https://stooq.com/q/l/?s=%5Edji&f=sd2t2ohlcvp&h&e=csv",
    "Error: 404 Not Found for https://stooq.com/q/l/?s=qqq.us&f=sd2t2ohlcvp&h&e=csv",
    "Error: 404 Not Found for https://stooq.com/q/l/?s=nvda.us&f=sd2t2ohlcvp&h&e=csv"
  ]
}
